odoo/addons/document_page_partner/README.rst
odoo/addons/document_page_partner/__init__.py
odoo/addons/document_page_partner/__manifest__.py
odoo/addons/document_page_partner/i18n/de.po
odoo/addons/document_page_partner/i18n/document_page_partner.pot
odoo/addons/document_page_partner/i18n/document_page_partner_id.pot
odoo/addons/document_page_partner/i18n/es.po
odoo/addons/document_page_partner/i18n/it.po
odoo/addons/document_page_partner/i18n/pt.po
odoo/addons/document_page_partner/models/__init__.py
odoo/addons/document_page_partner/models/document_page.py
odoo/addons/document_page_partner/readme/CONTRIBUTORS.md
odoo/addons/document_page_partner/readme/DESCRIPTION.md
odoo/addons/document_page_partner/readme/USAGE.md
odoo/addons/document_page_partner/static/description/icon.png
odoo/addons/document_page_partner/static/description/index.html
odoo/addons/document_page_partner/views/document_page.xml
odoo_addon_document_page_partner-18.0.1.0.0.2.dist-info/METADATA
odoo_addon_document_page_partner-18.0.1.0.0.2.dist-info/WHEEL
odoo_addon_document_page_partner-18.0.1.0.0.2.dist-info/top_level.txt
odoo_addon_document_page_partner-18.0.1.0.0.2.dist-info/RECORD
